[{"name":"Ecuador","continent":"Europa","officialCoin":"USD","isCountryVisitedMultipleTimes":true,"qtyCitiesToVisit":23,"visitedCities":[]},{"name":"Espana","continent":"Europa","officialCoin":"Euro","isCountryVisitedMultipleTimes":false,"qtyCitiesToVisit":43,"visitedCities":[{"name":"Madrid","isSafeCity":true,"lastVisitDate":"2022-07-23T23:55:13.538Z","qtyVisits":1,"placesToVisit":"la plaza, la iglesia"},{"name":"Murcia","isSafeCity":true,"lastVisitDate":"2023-01-24T00:03:35.591Z","qtyVisits":2,"placesToVisit":"cementerio"}]}]